chainplotter/__init__.py
chainplotter/cosmosis_getdist.py
chainplotter-1.0.1.dist-info/LICENSE
chainplotter-1.0.1.dist-info/METADATA
chainplotter-1.0.1.dist-info/WHEEL
chainplotter-1.0.1.dist-info/top_level.txt
chainplotter-1.0.1.dist-info/RECORD
