Metadata-Version: 2.1
Name: chainplotter
Version: 1.0.1
License-File: LICENSE
Requires-Dist: numpy
Requires-Dist: getdist ==1.5.1
Requires-Dist: pytest
Requires-Dist: sphinx-rtd-theme
